marathon/__init__.py
marathon/admin.py
marathon/apps.py
marathon/commands.py
marathon/mixins.py
marathon/models.py
marathon/__pycache__/__init__.cpython-310.pyc
marathon/__pycache__/admin.cpython-310.pyc
marathon/__pycache__/apps.cpython-310.pyc
marathon/__pycache__/commands.cpython-310.pyc
marathon/__pycache__/mixins.cpython-310.pyc
marathon/__pycache__/models.cpython-310.pyc
marathon/__pycache__/tests.cpython-310-pytest-6.2.5.pyc
marathon/__pycache__/tests.cpython-310-pytest-7.4.3.pyc
marathon/__pycache__/tests.cpython-310-pytest-8.2.1.pyc
marathon/migrations/0001_initial.py
marathon/migrations/__init__.py
marathon/migrations/__pycache__/0001_initial.cpython-310.pyc
marathon/migrations/__pycache__/__init__.cpython-310.pyc
django_marathon-0.1.dist-info/AUTHORS
django_marathon-0.1.dist-info/LICENCE
django_marathon-0.1.dist-info/METADATA
django_marathon-0.1.dist-info/WHEEL
django_marathon-0.1.dist-info/top_level.txt
django_marathon-0.1.dist-info/RECORD
