Metadata-Version: 2.1
Name: django-marathon
Version: 0.1
Summary: Helps manage single runner tasks that need to avoid concurrency issues.
Home-page: https://github.com/lazybird/django-marathon/
Author: 
Author-email: 
Keywords: Django single runner tasks concurrency concurrency-avoidance
License-File: LICENCE
License-File: AUTHORS
